[
    {
        "replyId":1,
        "questionId": 1,
        "authorId": "auth0|6432db77953ebdac04e8da15",
        "content": "In my opinion, the meaning of life is to pursue happiness and find fulfillment in our relationships and experiences.",
        "reCommentId": [3]
    },
    {
        "replyId":2,
        "questionId": 1,
        "authorId": "auth0|6432db77953ebdac04e8da15",
        "content": "In my opinion, the meaning of life is to pursue happiness and find fulfillment in our relationships and experiences.",
        "reCommentId": []
    }
]